jd_nf/__init__.py
jd_nf/nf_pj.py
jf_nf/__init__.py
jf_nf/nf_pj.py
jd_nf-0.0.2.dist-info/LICENSE
jd_nf-0.0.2.dist-info/METADATA
jd_nf-0.0.2.dist-info/WHEEL
jd_nf-0.0.2.dist-info/top_level.txt
jd_nf-0.0.2.dist-info/RECORD
