Metadata-Version: 2.1
Name: jd-nf
Version: 0.0.2
Summary: neufoundry sdk
Home-page: https://aidoc.jd.com/neufoundry/quickstart/overview.html
Author: tst
Author-email: tst@jd.com
License: UNKNOWN
Keywords: pip,datacanvas,eds,xiaoh
Platform: UNKNOWN
Classifier: Programming Language :: Python :: 3
Classifier: License :: OSI Approved :: MIT License
Classifier: Operating System :: OS Independent
